pyneuro_analyse/__init__.py
pyneuro_analyse/graphing.py
pyneuro_analyse/processing.py
pyneuro_analyse-0.1.12.dist-info/licenses/LICENCE.txt
pyneuro_analyse-0.1.12.dist-info/METADATA
pyneuro_analyse-0.1.12.dist-info/WHEEL
pyneuro_analyse-0.1.12.dist-info/top_level.txt
pyneuro_analyse-0.1.12.dist-info/RECORD
