Metadata-Version: 2.4
Name: pyneuro_analyse
Version: 0.1.12
Summary: Helper routines for stereotypical analysis of Neuroscience data, including Electrophysiological (Patch clamp), Behavioral and Ca-imaging (fiber photometry and single cell) data
Author-email: Denys Osypenko <adenys.osypenko@unil.ch>
Project-URL: Homepage, https://github.com/Mameli-Lab
Project-URL: Issues, https://github.com/Mameli-Lab
Classifier: Programming Language :: Python :: 3
Classifier: License :: OSI Approved :: MIT License
Classifier: Operating System :: OS Independent
Classifier: Intended Audience :: Education
Requires-Python: >=3.8
License-File: LICENCE.txt
Dynamic: license-file
